build/lib/build/lib/build/lib/build/lib/build/lib/google_artifactregistry_auth/tox_bootstrap.py
build/lib/build/lib/build/lib/build/lib/build/lib/keyrings/gauth.py
build/lib/build/lib/build/lib/build/lib/build/lib/tests/tox-plugin/setup.py
build/lib/build/lib/build/lib/build/lib/google_artifactregistry_auth/tox_bootstrap.py
build/lib/build/lib/build/lib/build/lib/keyrings/gauth.py
build/lib/build/lib/build/lib/build/lib/tests/tox-plugin/setup.py
build/lib/build/lib/build/lib/google_artifactregistry_auth/tox_bootstrap.py
build/lib/build/lib/build/lib/keyrings/gauth.py
build/lib/build/lib/build/lib/tests/tox-plugin/setup.py
build/lib/build/lib/google_artifactregistry_auth/tox_bootstrap.py
build/lib/build/lib/keyrings/gauth.py
build/lib/build/lib/tests/tox-plugin/setup.py
build/lib/google_artifactregistry_auth/tox_bootstrap.py
build/lib/keyrings/gauth.py
build/lib/tests/tox-plugin/setup.py
google_artifactregistry_auth/tox_bootstrap.py
keyrings/gauth.py
tests/tox-plugin/setup.py
tests/tox-plugin/tox.ini
keyrings.google_artifactregistry_auth_gcloud-1.1.4.dist-info/LICENSE
keyrings.google_artifactregistry_auth_gcloud-1.1.4.dist-info/METADATA
keyrings.google_artifactregistry_auth_gcloud-1.1.4.dist-info/WHEEL
keyrings.google_artifactregistry_auth_gcloud-1.1.4.dist-info/entry_points.txt
keyrings.google_artifactregistry_auth_gcloud-1.1.4.dist-info/top_level.txt
keyrings.google_artifactregistry_auth_gcloud-1.1.4.dist-info/RECORD
